py_s3_cache
