Metadata-Version: 1.0
Name: py-s3-cache
Version: 1.0.0
Summary: Super minimal python S3 cache
Home-page: https://github.com/nricklin/py-s3-cache
Author: Nate Ricklin
Author-email: nate.ricklin@gmail.com
License: MIT
Platform: UNKNOWN
